intlab/__init__.py
intlab/sapnet.py
intlab-1.4.7.dist-info/LICENSE
intlab-1.4.7.dist-info/METADATA
intlab-1.4.7.dist-info/WHEEL
intlab-1.4.7.dist-info/top_level.txt
intlab-1.4.7.dist-info/RECORD
