Metadata-Version: 2.1
Name: intlab
Version: 1.4.7
Summary: IISL: SAP-net
Home-page: https://github.com/takayasora/intlab
Download-URL: https://github.com/takayasora/intlab
Author: Sora Takaya
Author-email: so12ra16@outlook.jp
Maintainer: Sora Takaya
Maintainer-email: so12ra16@outlook.jp
License: MIT License
Classifier: Programming Language :: Python :: 2
Classifier: Programming Language :: Python :: 2.7
Classifier: Programming Language :: Python :: 3
Classifier: Programming Language :: Python :: 3.3
Classifier: Programming Language :: Python :: 3.4
Classifier: License :: OSI Approved :: MIT License
Requires-Python: >=3.6
License-File: LICENSE
Requires-Dist: pillow (>=9.5.0)
Requires-Dist: matplotlib (>=3.7.1)
Requires-Dist: pandas (>=2.0.0)
Requires-Dist: numpy (>=1.23.5)
Requires-Dist: seaborn (>=0.12.2)
Requires-Dist: japanize-matplotlib (>=1.1.3)
Requires-Dist: networkx (>=3.1)
